earthkit/plots/__init__.py
earthkit/plots/_plugins.py
earthkit/plots/ancillary.py
earthkit/plots/definitions.py
earthkit/plots/identifiers.py
earthkit/plots/quickmap.py
earthkit/plots/quickplot.py
earthkit/plots/resample.py
earthkit/plots/schemas.py
earthkit/plots/shortcuts.py
earthkit/plots/version.py
earthkit/plots/workflows.py
earthkit/plots/cli/__init__.py
earthkit/plots/cli/parsers.py
earthkit/plots/components/animations.py
earthkit/plots/components/extractors.py
earthkit/plots/components/figures.py
earthkit/plots/components/globes.py
earthkit/plots/components/layers.py
earthkit/plots/components/layouts.py
earthkit/plots/components/maps.py
earthkit/plots/components/subplots.py
earthkit/plots/components/ticks.py
earthkit/plots/components/tiles.py
earthkit/plots/data/geo/coastlines_low.json
earthkit/plots/data/geo/domains.yml
earthkit/plots/data/logos/ecmwf.png
earthkit/plots/data/static/fonts/Lato/Lato-Black.ttf
earthkit/plots/data/static/fonts/Lato/Lato-BlackItalic.ttf
earthkit/plots/data/static/fonts/Lato/Lato-Bold.ttf
earthkit/plots/data/static/fonts/Lato/Lato-BoldItalic.ttf
earthkit/plots/data/static/fonts/Lato/Lato-Italic.ttf
earthkit/plots/data/static/fonts/Lato/Lato-Light.ttf
earthkit/plots/data/static/fonts/Lato/Lato-LightItalic.ttf
earthkit/plots/data/static/fonts/Lato/Lato-Regular.ttf
earthkit/plots/data/static/fonts/Lato/Lato-Thin.ttf
earthkit/plots/data/static/fonts/Lato/Lato-ThinItalic.ttf
earthkit/plots/data/static/fonts/OpenSans/OFL.txt
earthkit/plots/data/static/fonts/OpenSans/OpenSans-Bold.ttf
earthkit/plots/data/static/fonts/OpenSans/OpenSans-BoldItalic.ttf
earthkit/plots/data/static/fonts/OpenSans/OpenSans-ExtraBold.ttf
earthkit/plots/data/static/fonts/OpenSans/OpenSans-ExtraBoldItalic.ttf
earthkit/plots/data/static/fonts/OpenSans/OpenSans-Italic.ttf
earthkit/plots/data/static/fonts/OpenSans/OpenSans-Light.ttf
earthkit/plots/data/static/fonts/OpenSans/OpenSans-LightItalic.ttf
earthkit/plots/data/static/fonts/OpenSans/OpenSans-Medium.ttf
earthkit_plots-0.5.1.dist-info/licenses/LICENCE
earthkit_plots-0.5.1.dist-info/METADATA
earthkit_plots-0.5.1.dist-info/WHEEL
earthkit_plots-0.5.1.dist-info/top_level.txt
earthkit_plots-0.5.1.dist-info/RECORD
