Metadata-Version: 2.4
Name: earthkit-plots
Version: 0.5.1
Summary: Visualisation tools for earth science data
Author-email: "European Centre for Medium-Range Weather Forecasts (ECMWF)" <software.support@ecmwf.int>
License: Apache License Version 2.0
Project-URL: Documentation, https://earthkit-plots.readthedocs.io/
Project-URL: Homepage, https://github.com/ecmwf/earthkit-plots/
Project-URL: Issues, https://github.com/ecmwf/earthkit-plots.issues
Project-URL: Repository, https://github.com/ecmwf/earthkit-plots/
Classifier: Development Status :: 2 - Pre-Alpha
Classifier: Intended Audience :: Developers
Classifier: License :: OSI Approved :: Apache Software License
Classifier: Operating System :: OS Independent
Classifier: Programming Language :: Python :: 3 :: Only
Classifier: Programming Language :: Python :: 3.8
Classifier: Programming Language :: Python :: 3.9
Classifier: Programming Language :: Python :: 3.10
Classifier: Programming Language :: Python :: 3.11
Classifier: Programming Language :: Python :: 3.12
Classifier: Programming Language :: Python :: Implementation :: CPython
Classifier: Programming Language :: Python :: Implementation :: PyPy
Requires-Python: >=3.8
License-File: LICENCE
Requires-Dist: earthkit-data
Requires-Dist: earthkit-plots-default-styles>=0.1.3
Requires-Dist: cartopy>=0.22.0
Requires-Dist: pint
Requires-Dist: matplotlib
Requires-Dist: pandas
Requires-Dist: plotly
Requires-Dist: pyyaml
Requires-Dist: numpy
Requires-Dist: adjustText
Provides-Extra: geocoding
Requires-Dist: reverse-geocode; extra == "geocoding"
Provides-Extra: healpix
Requires-Dist: healpy; extra == "healpix"
Provides-Extra: test
Requires-Dist: nbconvert; extra == "test"
Requires-Dist: nbformat; extra == "test"
Requires-Dist: pytest; extra == "test"
Requires-Dist: pytest-mpl; extra == "test"
Requires-Dist: pytest-cov; extra == "test"
Requires-Dist: pytest-forked; extra == "test"
Requires-Dist: pytest-timeout; extra == "test"
Dynamic: license-file
